version3900-3.9.0.dist-info/METADATA
version3900-3.9.0.dist-info/WHEEL
version3900-3.9.0.dist-info/entry_points.txt
version3900/__init__.py
version3900/build_version.py
version3900-3.9.0.dist-info/RECORD
