Metadata-Version: 2.1
Name: version3900
Version: 3.9.0
Summary: Python versioning package
Author-Email: "D. Alex Graham" <alex@aode.space>
License: MIT
Requires-Python: >=3.9
